[
    {
        "id": "1",
        "name": "Dr Ross Perry",
        "education": "MBBS",
        "type": "Aesthetic Doctor",
        "img": "https://cosmedics-s3-bucket.s3.eu-west-2.amazonaws.com/wp-content/uploads/2020/05/16122011/dr-ross-perry-500x500.jpg"
    },
    
    {
        "id": "2",
        "name": "Ms Aoife Turner",
        "education": "MB Bch BAO FA, EBOPRAS ",
        "type": "Cosmetic Surgeon",
        "img": "https://cosmedics-s3-bucket.s3.eu-west-2.amazonaws.com/wp-content/uploads/2020/05/20081708/Ms-Aoife-Turner-500x500.jpg"
    },
    
    {
        "id": "3",
        "name": "Mr Michail Malandrakis",
        "education": "FEBOPHTH L7CERT(AESTH)",
        "type": "Consultant Surgeon",
        "img": "https://cosmedics-s3-bucket.s3.eu-west-2.amazonaws.com/wp-content/uploads/2020/07/20090128/Mr-Michail-Malandrakis-500x500.jpg"
    },
    
    {
        "id": "4",
        "name": "Mr Paul Caine",
        "education": "Plastic Surgeon",
        "type": "London",
        "img": "https://cosmedics-s3-bucket.s3.eu-west-2.amazonaws.com/wp-content/uploads/2021/04/12120535/aesthetics-doctor-profile-300x300.jpg"
    },
    
    {
        "id": "5",
        "name": "Dr Maria Miranda",
        "education": "MD, PhD, FEBOPRAS",
        "type": "Plastic Surgeon",
        "img": "https://cosmedics-s3-bucket.s3.eu-west-2.amazonaws.com/wp-content/uploads/2021/10/11190029/Dr-Maria-Miranda.jpg"
    },
    
    {
        "id": "6",
        "name": "Mr Parameswaran Sridhar",
        "education": "MBBS, FRCS",
        "type": "Vascular Surgeon",
        "img": "https://cosmedics-s3-bucket.s3.eu-west-2.amazonaws.com/wp-content/uploads/2020/07/20091140/Mr-Parameswaran-Sridhar-500x500.jpg"
    },
    
    {
        "id": "7",
        "name": "Mr Alex Von Roon",
        "education": "MB CHB PHD FRCS",
        "type": "Consultant Colorectal Surgeon",
        "img": "https://cosmedics-s3-bucket.s3.eu-west-2.amazonaws.com/wp-content/uploads/2020/07/20092045/Mr-Alex-von-Roon-500x500.jpg"
    },
    
    {
        "id": "8",
        "name": "Dr Rhys Stevens",
        "education": "MBBS, BSCI, MRCGP",
        "type": "Aesthetic Doctor",
        "img": "https://cosmedics-s3-bucket.s3.eu-west-2.amazonaws.com/wp-content/uploads/2020/05/20085209/Dr-Rhys-Stevens-500x500.jpg"
    },
    
    {
        "id": "9",
        "name": "Dr Lydia Ioannidi",
        "education": "Aesthetic Doctor",
        "type": "Harley Street & Putney",
        "img": "https://cosmedics-s3-bucket.s3.eu-west-2.amazonaws.com/wp-content/uploads/2021/04/12120535/aesthetics-doctor-profile-300x300.jpg"
    }
    
]